BasicLibrary/.env.default
BasicLibrary/.README.md
BasicLibrary/__init__.py
BasicLibrary/__projectConfig.ini
BasicLibrary/__projectHelper.py
BasicLibrary/_res/__init__.py
BasicLibrary/_res/pre-commit.auto-increase-version
BasicLibrary/_res/readme.md
BasicLibrary/biz/__init__.py
BasicLibrary/biz/adobe/__init__.py
BasicLibrary/biz/adobe/photoShopHelper.py
BasicLibrary/biz/stock/__init__.py
BasicLibrary/biz/stock/stockHelper.py
BasicLibrary/configHelper.py
BasicLibrary/data/00.README.md
BasicLibrary/data/__init__.py
BasicLibrary/data/base64Helper.py
BasicLibrary/data/chineseData.py
BasicLibrary/data/chineseHelper.py
BasicLibrary/data/collectionHelper.py
BasicLibrary/data/convertor.py
BasicLibrary/data/dateTimeHelper.py
BasicLibrary/data/dateTimePlaceHolderHelper.py
BasicLibrary/data/dictHelper.py
BasicLibrary/data/enumBase.py
BasicLibrary/data/enumHelper.py
BasicLibrary/data/htmlHelper.py
BasicLibrary/data/imageHelper.py
BasicLibrary/data/listHelper.py
BasicLibrary/data/lunarDate.py
BasicLibrary/data/mediaHelper.py
BasicLibrary/data/mediaTypes.py
BasicLibrary/data/numberHelper.py
BasicLibrary/data/objectHelper.py
BasicLibrary/data/pandasHelper.py
BasicLibrary/data/randomHelper.py
BasicLibrary/data/reflectHelper.py
BasicLibrary/data/regexHelper.py
BasicLibrary/data/setHelper.py
BasicLibrary/data/stringHelper.py
BasicLibrary/data/tomlMate.py
BasicLibrary/data/tupleHelper.py
BasicLibrary/data/typeEnum.py
BasicLibrary/data/typeHelper.py
BasicLibrary/data/uuidHelper.py
BasicLibrary/dataBase/.README.md
BasicLibrary/dataBase/__init__.py
BasicLibrary/dataBase/databaseClient.py
BasicLibrary/dataBase/databaseDDL.py
BasicLibrary/dataBase/databaseEnum.py
BasicLibrary/dataBase/databaseHelper.py
BasicLibrary/dataBase/databaseMate.py
BasicLibrary/dataBase/databaseUnitTest.py
BasicLibrary/dataBase/MongoDB/__init__.py
BasicLibrary/dataBase/MongoDB/ddl.py
BasicLibrary/dataBase/MongoDB/helper.py
BasicLibrary/dataBase/MongoDB/mate.py
BasicLibrary/dataBase/MySql/__init__.py
basiclibrary_py-0.6.60.dist-info/METADATA
basiclibrary_py-0.6.60.dist-info/WHEEL
basiclibrary_py-0.6.60.dist-info/RECORD
