Metadata-Version: 2.4
Name: BasicLibrary.PY
Version: 0.6.60
Summary: 
Author: 解大劦
Author-email: 9727005@qq.com
Requires-Python: >=3.12
Classifier: Programming Language :: Python :: 3
Classifier: Programming Language :: Python :: 3.12
Classifier: Programming Language :: Python :: 3.13
Classifier: Programming Language :: Python :: 3.14
Requires-Dist: chardet (>=5.2.0,<6.0.0)
Requires-Dist: filetype (>=1.2.0,<2.0.0)
Requires-Dist: pandas (>=2.2.1,<3.0.0)
Requires-Dist: pillow (>=10.2.0,<11.0.0)
Requires-Dist: python-dotenv (>=1.0.1,<2.0.0)
Requires-Dist: ulid-py (>=1.1.0,<2.0.0)
Requires-Dist: xlwings (>=0.31.6,<0.32.0)
Requires-Dist: zhdate (>=0.1,<0.2)
